idingbot/__init__.py
idingbot/constant/__init__.py
idingbot/constant/interface.py
idingbot/core/__init__.py
idingbot/core/core.py
idingbot/core/extension.py
idingbot/core/log.py
idingbot/dll/WxWork.dll
idingbot/dll/__init__.py
idingbot/dll/transfer.dll
module/__init__.py
module/constant/__init__.py
module/constant/interface.py
module/core/__init__.py
module/core/core.py
module/core/extension.py
module/core/log.py
module/dll/__init__.py
idingbot-0.0.6.dist-info/LICENSE
idingbot-0.0.6.dist-info/METADATA
idingbot-0.0.6.dist-info/WHEEL
idingbot-0.0.6.dist-info/top_level.txt
idingbot-0.0.6.dist-info/RECORD
